npapibench/__init__.py
npapibench/bench.py
npapibench/cimpl.cp39-win_amd64.pyd
npapibench/conftest.py
npapibench/pyimpl.py
npapibench/functimer/__init__.py
npapibench/functimer/_timeapi.cp39-win_amd64.pyd
npapibench/functimer/_timeresult.cp39-win_amd64.pyd
npapibench/functimer/_timeunit.cp39-win_amd64.pyd
npapibench/functimer/tests/__init__.py
npapibench/functimer/tests/test_TimeResult.py
npapibench/functimer/tests/test__timeapi.py
npapibench/tests/__init__.py
npapibench/tests/conftest.py
npapibench/tests/test_bench.py
npapibench/tests/test_cimpl.py
numpy_api_bench-0.1.0.dist-info/LICENSE
numpy_api_bench-0.1.0.dist-info/METADATA
numpy_api_bench-0.1.0.dist-info/WHEEL
numpy_api_bench-0.1.0.dist-info/entry_points.txt
numpy_api_bench-0.1.0.dist-info/top_level.txt
numpy_api_bench-0.1.0.dist-info/RECORD
