Metadata-Version: 2.1
Name: numpy-api-bench
Version: 0.1.0
Summary: A small Python package showcasing speed differences between NumPy's Python and C APIs.
Home-page: https://github.com/phetdam/numpy-api-bench
Author: Derek Huang
Author-email: djh458@stern.nyu.edu
License: MIT
Project-URL: Source, https://github.com/phetdam/numpy-api-bench
Platform: UNKNOWN
Classifier: License :: OSI Approved :: MIT License
Classifier: Operating System :: POSIX :: Linux
Classifier: Operating System :: Microsoft :: Windows
Classifier: Operating System :: MacOS
Classifier: Programming Language :: Python :: 3.6
Classifier: Programming Language :: Python :: 3.7
Classifier: Programming Language :: Python :: 3.8
Classifier: Programming Language :: Python :: 3.9
Requires-Python: >=3.6
Provides-Extra: tests
License-File: LICENSE
